{
  "genre_id": "cinematic",
  "genre_name": "Cinematic",
  "category": "Presentation",
  "supply_count": 2816,
  "demand_count": 4589,
  "growth_pct": 18.9,
  "opportunity_score": 9.9,
  "opportunity_class": "Excellent",
  "heatmap": {
    "reddit": 1377,
    "youtube": 1377,
    "tiktok": 688,
    "steam": 688,
    "bluesky": 574
  },
  "timeline": [
    {
      "month": "Jan",
      "count": 1989
    },
    {
      "month": "Feb",
      "count": 2709
    },
    {
      "month": "Mar",
      "count": 3293
    },
    {
      "month": "Apr",
      "count": 3691
    },
    {
      "month": "May",
      "count": 4633
    },
    {
      "month": "Jun",
      "count": 4406
    }
  ],
  "related_network": [
    "Singleplayer",
    "Indie",
    "Action",
    "Action-Adventure",
    "Assassins",
    "Pirates"
  ],
  "games": [
    {
      "app_id": 3751950,
      "name": "Assassin's Creed Black Flag Resynced",
      "capsule_url": "https://shared.fastly.steamstatic.com/store_item_assets/steam/apps/3751950/header.jpg",
      "trend_score": 74,
      "growth_pct": 531,
      "sentiment_positive": 84,
      "tags": [
        "Action-Adventure",
        "Assassins",
        "Pirates",
        "Naval Combat",
        "Stealth",
        "Exploration",
        "Open World",
        "Third Person",
        "Adventure",
        "Historical"
      ]
    },
    {
      "app_id": 1172470,
      "name": "Apex Legends\u2122",
      "capsule_url": "https://shared.fastly.steamstatic.com/store_item_assets/steam/apps/1172470/header.jpg",
      "trend_score": 90,
      "growth_pct": 99,
      "sentiment_positive": 92,
      "tags": [
        "Free to Play",
        "Battle Royale",
        "Multiplayer",
        "FPS",
        "Shooter",
        "First-Person",
        "PvP",
        "Action",
        "Hero Shooter",
        "Team-Based"
      ]
    },
    {
      "app_id": 2183900,
      "name": "Warhammer 40,000: Space Marine 2",
      "capsule_url": "https://shared.fastly.steamstatic.com/store_item_assets/steam/apps/2183900/header.jpg",
      "trend_score": 92,
      "growth_pct": 485,
      "sentiment_positive": 85,
      "tags": [
        "Cinematic",
        "Indie",
        "Singleplayer"
      ]
    },
    {
      "app_id": 3017860,
      "name": "DOOM: The Dark Ages",
      "capsule_url": "https://shared.fastly.steamstatic.com/store_item_assets/steam/apps/3017860/header.jpg",
      "trend_score": 98,
      "growth_pct": 546,
      "sentiment_positive": 91,
      "tags": [
        "Cinematic",
        "Indie",
        "Singleplayer"
      ]
    },
    {
      "app_id": 2050650,
      "name": "Resident Evil 4",
      "capsule_url": "https://shared.fastly.steamstatic.com/store_item_assets/steam/apps/2050650/header.jpg",
      "trend_score": 85,
      "growth_pct": 197,
      "sentiment_positive": 91,
      "tags": [
        "Cinematic",
        "Indie",
        "Singleplayer"
      ]
    },
    {
      "app_id": 3764200,
      "name": "Resident Evil Requiem",
      "capsule_url": "https://shared.fastly.steamstatic.com/store_item_assets/steam/apps/3764200/header.jpg",
      "trend_score": 78,
      "growth_pct": 472,
      "sentiment_positive": 78,
      "tags": [
        "Cinematic",
        "Indie",
        "Singleplayer"
      ]
    },
    {
      "app_id": 1462040,
      "name": "FINAL FANTASY VII REMAKE INTERGRADE",
      "capsule_url": "https://shared.fastly.steamstatic.com/store_item_assets/steam/apps/1462040/header.jpg",
      "trend_score": 70,
      "growth_pct": 238,
      "sentiment_positive": 96,
      "tags": [
        "Cinematic",
        "Indie",
        "Singleplayer"
      ]
    },
    {
      "app_id": 2322010,
      "name": "God of War Ragnar\u00f6k",
      "capsule_url": "https://shared.fastly.steamstatic.com/store_item_assets/steam/apps/2322010/header.jpg",
      "trend_score": 97,
      "growth_pct": 363,
      "sentiment_positive": 83,
      "tags": [
        "Cinematic",
        "Indie",
        "Singleplayer"
      ]
    },
    {
      "app_id": 3768760,
      "name": "007 First Light",
      "capsule_url": "https://shared.fastly.steamstatic.com/store_item_assets/steam/apps/3768760/header.jpg",
      "trend_score": 76,
      "growth_pct": 264,
      "sentiment_positive": 80,
      "tags": [
        "Cinematic",
        "Indie",
        "Singleplayer"
      ]
    },
    {
      "app_id": 1371980,
      "name": "No Rest for the Wicked",
      "capsule_url": "https://shared.fastly.steamstatic.com/store_item_assets/steam/apps/1371980/header.jpg",
      "trend_score": 92,
      "growth_pct": 443,
      "sentiment_positive": 80,
      "tags": [
        "Cinematic",
        "Indie",
        "Singleplayer"
      ]
    },
    {
      "app_id": 1888930,
      "name": "The Last of Us\u2122 Part I",
      "capsule_url": "https://shared.fastly.steamstatic.com/store_item_assets/steam/apps/1888930/header.jpg",
      "trend_score": 97,
      "growth_pct": 493,
      "sentiment_positive": 85,
      "tags": [
        "Cinematic",
        "Indie",
        "Singleplayer"
      ]
    },
    {
      "app_id": 1222140,
      "name": "Detroit: Become Human",
      "capsule_url": "https://shared.fastly.steamstatic.com/store_item_assets/steam/apps/1222140/header.jpg",
      "trend_score": 70,
      "growth_pct": 374,
      "sentiment_positive": 88,
      "tags": [
        "Cinematic",
        "Indie",
        "Singleplayer"
      ]
    },
    {
      "app_id": 4032350,
      "name": "EA SPORTS\u2122 College Football 27",
      "capsule_url": "https://shared.fastly.steamstatic.com/store_item_assets/steam/apps/4032350/header.jpg",
      "trend_score": 80,
      "growth_pct": 437,
      "sentiment_positive": 86,
      "tags": [
        "Cinematic",
        "Indie",
        "Singleplayer"
      ]
    },
    {
      "app_id": 1659040,
      "name": "HITMAN World of Assassination",
      "capsule_url": "https://shared.fastly.steamstatic.com/store_item_assets/steam/apps/1659040/header.jpg",
      "trend_score": 82,
      "growth_pct": 232,
      "sentiment_positive": 82,
      "tags": [
        "Cinematic",
        "Indie",
        "Singleplayer"
      ]
    },
    {
      "app_id": 2592160,
      "name": "Dispatch",
      "capsule_url": "https://shared.fastly.steamstatic.com/store_item_assets/steam/apps/2592160/header.jpg",
      "trend_score": 80,
      "growth_pct": 306,
      "sentiment_positive": 92,
      "tags": [
        "Cinematic",
        "Indie",
        "Singleplayer"
      ]
    },
    {
      "app_id": 2357570,
      "name": "Overwatch\u00ae",
      "capsule_url": "https://shared.fastly.steamstatic.com/store_item_assets/steam/apps/2357570/header.jpg",
      "trend_score": 81,
      "growth_pct": 27,
      "sentiment_positive": 94,
      "tags": [
        "Cinematic",
        "Indie",
        "Singleplayer"
      ]
    },
    {
      "app_id": 2909400,
      "name": "FINAL FANTASY VII REBIRTH",
      "capsule_url": "https://shared.fastly.steamstatic.com/store_item_assets/steam/apps/2909400/header.jpg",
      "trend_score": 84,
      "growth_pct": 414,
      "sentiment_positive": 84,
      "tags": [
        "Cinematic",
        "Indie",
        "Singleplayer"
      ]
    },
    {
      "app_id": 1659420,
      "name": "UNCHARTED\u2122: Legacy of Thieves Collection",
      "capsule_url": "https://shared.fastly.steamstatic.com/store_item_assets/steam/apps/1659420/header.jpg",
      "trend_score": 79,
      "growth_pct": 128,
      "sentiment_positive": 96,
      "tags": [
        "Cinematic",
        "Indie",
        "Singleplayer"
      ]
    },
    {
      "app_id": 3469450,
      "name": "DOOM: The Dark Ages | Revelations",
      "capsule_url": "https://shared.fastly.steamstatic.com/store_item_assets/steam/apps/3469450/header.jpg",
      "trend_score": 73,
      "growth_pct": 113,
      "sentiment_positive": 83,
      "tags": [
        "Cinematic",
        "Indie",
        "Singleplayer"
      ]
    },
    {
      "app_id": 1384160,
      "name": "GUILTY GEAR -STRIVE-",
      "capsule_url": "https://shared.fastly.steamstatic.com/store_item_assets/steam/apps/1384160/header.jpg",
      "trend_score": 90,
      "growth_pct": 418,
      "sentiment_positive": 79,
      "tags": [
        "Cinematic",
        "Indie",
        "Singleplayer"
      ]
    },
    {
      "app_id": 1182900,
      "name": "A Plague Tale: Requiem",
      "capsule_url": "https://shared.fastly.steamstatic.com/store_item_assets/steam/apps/1182900/header.jpg",
      "trend_score": 77,
      "growth_pct": 489,
      "sentiment_positive": 95,
      "tags": [
        "Cinematic",
        "Indie",
        "Singleplayer"
      ]
    },
    {
      "app_id": 1643320,
      "name": "S.T.A.L.K.E.R. 2: Heart of Chornobyl",
      "capsule_url": "https://shared.fastly.steamstatic.com/store_item_assets/steam/apps/1643320/header.jpg",
      "trend_score": 82,
      "growth_pct": 289,
      "sentiment_positive": 78,
      "tags": [
        "Cinematic",
        "Indie",
        "Singleplayer"
      ]
    },
    {
      "app_id": 2947440,
      "name": "SILENT HILL f",
      "capsule_url": "https://shared.fastly.steamstatic.com/store_item_assets/steam/apps/2947440/header.jpg",
      "trend_score": 95,
      "growth_pct": 479,
      "sentiment_positive": 78,
      "tags": [
        "Cinematic",
        "Indie",
        "Singleplayer"
      ]
    },
    {
      "app_id": 2515020,
      "name": "FINAL FANTASY XVI",
      "capsule_url": "https://shared.fastly.steamstatic.com/store_item_assets/steam/apps/2515020/header.jpg",
      "trend_score": 72,
      "growth_pct": 80,
      "sentiment_positive": 91,
      "tags": [
        "Cinematic",
        "Indie",
        "Singleplayer"
      ]
    },
    {
      "app_id": 812140,
      "name": "Assassin's Creed\u00ae Odyssey",
      "capsule_url": "https://shared.fastly.steamstatic.com/store_item_assets/steam/apps/812140/header.jpg",
      "trend_score": 90,
      "growth_pct": 86,
      "sentiment_positive": 83,
      "tags": [
        "Cinematic",
        "Indie",
        "Singleplayer"
      ]
    }
  ]
}