{
  "genre_id": "cute",
  "genre_name": "Cute",
  "category": "Theme",
  "supply_count": 1666,
  "demand_count": 1626,
  "growth_pct": 8.6,
  "opportunity_score": 9.9,
  "opportunity_class": "Excellent",
  "heatmap": {
    "reddit": 488,
    "youtube": 488,
    "tiktok": 244,
    "steam": 244,
    "bluesky": 181
  },
  "timeline": [
    {
      "month": "Jan",
      "count": 640
    },
    {
      "month": "Feb",
      "count": 928
    },
    {
      "month": "Mar",
      "count": 1177
    },
    {
      "month": "Apr",
      "count": 1249
    },
    {
      "month": "May",
      "count": 1558
    },
    {
      "month": "Jun",
      "count": 1508
    }
  ],
  "related_network": [
    "Indie",
    "Singleplayer",
    "Multiplayer",
    "Casual",
    "Party Game",
    "Hidden Object"
  ],
  "games": [
    {
      "app_id": 4704690,
      "name": "MECCHA CHAMELEON",
      "capsule_url": "https://shared.fastly.steamstatic.com/store_item_assets/steam/apps/4704690/header.jpg",
      "trend_score": 98,
      "growth_pct": 199,
      "sentiment_positive": 91,
      "tags": [
        "Multiplayer",
        "Casual",
        "Party Game",
        "Hidden Object",
        "Funny",
        "Hand-drawn",
        "Online Co-Op",
        "Comedy",
        "Stealth",
        "Colorful"
      ]
    },
    {
      "app_id": 413150,
      "name": "Stardew Valley",
      "capsule_url": "https://shared.fastly.steamstatic.com/store_item_assets/steam/apps/413150/header.jpg",
      "trend_score": 76,
      "growth_pct": 232,
      "sentiment_positive": 90,
      "tags": [
        "Farming Sim",
        "Pixel Graphics",
        "Multiplayer",
        "Life Sim",
        "RPG",
        "Relaxing",
        "Simulation",
        "Agriculture",
        "Crafting",
        "Indie"
      ]
    },
    {
      "app_id": 703080,
      "name": "Planet Zoo",
      "capsule_url": "https://shared.fastly.steamstatic.com/store_item_assets/steam/apps/703080/header.jpg",
      "trend_score": 76,
      "growth_pct": 32,
      "sentiment_positive": 86,
      "tags": [
        "Cute",
        "Indie",
        "Singleplayer"
      ]
    },
    {
      "app_id": 1118520,
      "name": "Paralives",
      "capsule_url": "https://shared.fastly.steamstatic.com/store_item_assets/steam/apps/1118520/header.jpg",
      "trend_score": 87,
      "growth_pct": 441,
      "sentiment_positive": 78,
      "tags": [
        "Cute",
        "Indie",
        "Singleplayer"
      ]
    },
    {
      "app_id": 2246340,
      "name": "Monster Hunter Wilds",
      "capsule_url": "https://shared.fastly.steamstatic.com/store_item_assets/steam/apps/2246340/header.jpg",
      "trend_score": 94,
      "growth_pct": 504,
      "sentiment_positive": 93,
      "tags": [
        "Cute",
        "Indie",
        "Singleplayer"
      ]
    },
    {
      "app_id": 1222670,
      "name": "The Sims\u2122 4",
      "capsule_url": "https://shared.fastly.steamstatic.com/store_item_assets/steam/apps/1222670/header.jpg",
      "trend_score": 93,
      "growth_pct": 390,
      "sentiment_positive": 80,
      "tags": [
        "Cute",
        "Indie",
        "Singleplayer"
      ]
    },
    {
      "app_id": 2552430,
      "name": "KINGDOM HEARTS -HD 1.5+2.5 ReMIX-",
      "capsule_url": "https://shared.fastly.steamstatic.com/store_item_assets/steam/apps/2552430/header.jpg",
      "trend_score": 79,
      "growth_pct": 137,
      "sentiment_positive": 85,
      "tags": [
        "Cute",
        "Indie",
        "Singleplayer"
      ]
    },
    {
      "app_id": 2209900,
      "name": "Moonlight Peaks",
      "capsule_url": "https://shared.fastly.steamstatic.com/store_item_assets/steam/apps/2209900/header.jpg",
      "trend_score": 72,
      "growth_pct": 534,
      "sentiment_positive": 82,
      "tags": [
        "Cute",
        "Indie",
        "Singleplayer"
      ]
    },
    {
      "app_id": 312520,
      "name": "Rain World",
      "capsule_url": "https://shared.fastly.steamstatic.com/store_item_assets/steam/apps/312520/header.jpg",
      "trend_score": 77,
      "growth_pct": 368,
      "sentiment_positive": 87,
      "tags": [
        "Cute",
        "Indie",
        "Singleplayer"
      ]
    },
    {
      "app_id": 431960,
      "name": "Wallpaper Engine",
      "capsule_url": "https://shared.fastly.steamstatic.com/store_item_assets/steam/apps/431960/header.jpg",
      "trend_score": 81,
      "growth_pct": 24,
      "sentiment_positive": 83,
      "tags": [
        "Cute",
        "Indie",
        "Singleplayer"
      ]
    },
    {
      "app_id": 1984270,
      "name": "Digimon Story Time Stranger",
      "capsule_url": "https://shared.fastly.steamstatic.com/store_item_assets/steam/apps/1984270/header.jpg",
      "trend_score": 75,
      "growth_pct": 47,
      "sentiment_positive": 88,
      "tags": [
        "Cute",
        "Indie",
        "Singleplayer"
      ]
    },
    {
      "app_id": 1313140,
      "name": "Cult of the Lamb",
      "capsule_url": "https://shared.fastly.steamstatic.com/store_item_assets/steam/apps/1313140/header.jpg",
      "trend_score": 80,
      "growth_pct": 214,
      "sentiment_positive": 87,
      "tags": [
        "Cute",
        "Indie",
        "Singleplayer"
      ]
    },
    {
      "app_id": 1030300,
      "name": "Hollow Knight: Silksong",
      "capsule_url": "https://shared.fastly.steamstatic.com/store_item_assets/steam/apps/1030300/header.jpg",
      "trend_score": 71,
      "growth_pct": 414,
      "sentiment_positive": 86,
      "tags": [
        "Cute",
        "Indie",
        "Singleplayer"
      ]
    },
    {
      "app_id": 367520,
      "name": "Hollow Knight",
      "capsule_url": "https://shared.fastly.steamstatic.com/store_item_assets/steam/apps/367520/header.jpg",
      "trend_score": 78,
      "growth_pct": 58,
      "sentiment_positive": 90,
      "tags": [
        "Cute",
        "Indie",
        "Singleplayer"
      ]
    },
    {
      "app_id": 4380490,
      "name": "Cat Mail Co.",
      "capsule_url": "https://shared.fastly.steamstatic.com/store_item_assets/steam/apps/4380490/header.jpg",
      "trend_score": 71,
      "growth_pct": 453,
      "sentiment_positive": 93,
      "tags": [
        "Cute",
        "Indie",
        "Singleplayer"
      ]
    },
    {
      "app_id": 4162040,
      "name": "Zenless Zone Zero",
      "capsule_url": "https://shared.fastly.steamstatic.com/store_item_assets/steam/apps/4162040/header.jpg",
      "trend_score": 88,
      "growth_pct": 238,
      "sentiment_positive": 79,
      "tags": [
        "Cute",
        "Indie",
        "Singleplayer"
      ]
    },
    {
      "app_id": 686060,
      "name": "Mewgenics",
      "capsule_url": "https://shared.fastly.steamstatic.com/store_item_assets/steam/apps/686060/header.jpg",
      "trend_score": 80,
      "growth_pct": 180,
      "sentiment_positive": 80,
      "tags": [
        "Cute",
        "Indie",
        "Singleplayer"
      ]
    },
    {
      "app_id": 2185060,
      "name": "Two Point Museum",
      "capsule_url": "https://shared.fastly.steamstatic.com/store_item_assets/steam/apps/2185060/header.jpg",
      "trend_score": 77,
      "growth_pct": 521,
      "sentiment_positive": 91,
      "tags": [
        "Cute",
        "Indie",
        "Singleplayer"
      ]
    },
    {
      "app_id": 1332010,
      "name": "Stray",
      "capsule_url": "https://shared.fastly.steamstatic.com/store_item_assets/steam/apps/1332010/header.jpg",
      "trend_score": 79,
      "growth_pct": 347,
      "sentiment_positive": 90,
      "tags": [
        "Cute",
        "Indie",
        "Singleplayer"
      ]
    },
    {
      "app_id": 3935020,
      "name": "Backyard Baseball",
      "capsule_url": "https://shared.fastly.steamstatic.com/store_item_assets/steam/apps/3935020/header.jpg",
      "trend_score": 98,
      "growth_pct": 88,
      "sentiment_positive": 96,
      "tags": [
        "Cute",
        "Indie",
        "Singleplayer"
      ]
    },
    {
      "app_id": 728880,
      "name": "Overcooked! 2",
      "capsule_url": "https://shared.fastly.steamstatic.com/store_item_assets/steam/apps/728880/header.jpg",
      "trend_score": 80,
      "growth_pct": 535,
      "sentiment_positive": 93,
      "tags": [
        "Cute",
        "Indie",
        "Singleplayer"
      ]
    },
    {
      "app_id": 962130,
      "name": "Grounded",
      "capsule_url": "https://shared.fastly.steamstatic.com/store_item_assets/steam/apps/962130/header.jpg",
      "trend_score": 71,
      "growth_pct": 284,
      "sentiment_positive": 90,
      "tags": [
        "Cute",
        "Indie",
        "Singleplayer"
      ]
    },
    {
      "app_id": 3357650,
      "name": "PRAGMATA",
      "capsule_url": "https://shared.fastly.steamstatic.com/store_item_assets/steam/apps/3357650/header.jpg",
      "trend_score": 90,
      "growth_pct": 294,
      "sentiment_positive": 95,
      "tags": [
        "Cute",
        "Indie",
        "Singleplayer"
      ]
    },
    {
      "app_id": 4025700,
      "name": "Heartopia",
      "capsule_url": "https://shared.fastly.steamstatic.com/store_item_assets/steam/apps/4025700/header.jpg",
      "trend_score": 90,
      "growth_pct": 490,
      "sentiment_positive": 95,
      "tags": [
        "Cute",
        "Indie",
        "Singleplayer"
      ]
    },
    {
      "app_id": 2707930,
      "name": "Palia",
      "capsule_url": "https://shared.fastly.steamstatic.com/store_item_assets/steam/apps/2707930/header.jpg",
      "trend_score": 81,
      "growth_pct": 221,
      "sentiment_positive": 90,
      "tags": [
        "Cute",
        "Indie",
        "Singleplayer"
      ]
    }
  ]
}