{
  "genre_id": "emotional",
  "genre_name": "Emotional",
  "category": "Presentation",
  "supply_count": 0,
  "demand_count": 1949,
  "growth_pct": 1.5,
  "opportunity_score": 9.9,
  "opportunity_class": "Excellent",
  "heatmap": {
    "reddit": 585,
    "youtube": 585,
    "tiktok": 292,
    "steam": 292,
    "bluesky": 195
  },
  "timeline": [
    {
      "month": "Jan",
      "count": 814
    },
    {
      "month": "Feb",
      "count": 1078
    },
    {
      "month": "Mar",
      "count": 1334
    },
    {
      "month": "Apr",
      "count": 1646
    },
    {
      "month": "May",
      "count": 1689
    },
    {
      "month": "Jun",
      "count": 1971
    }
  ],
  "related_network": [
    "Indie",
    "Singleplayer",
    "Atmospheric"
  ],
  "games": [
    {
      "app_id": 215325,
      "name": "Emotional Quest",
      "capsule_url": "https://shared.fastly.steamstatic.com/store_item_assets/steam/apps/215325/header.jpg",
      "trend_score": 91,
      "growth_pct": 64,
      "sentiment_positive": 95,
      "tags": [
        "Emotional",
        "Indie",
        "Singleplayer",
        "Atmospheric"
      ]
    },
    {
      "app_id": 1431310,
      "name": "Emotional Chronicles",
      "capsule_url": "https://shared.fastly.steamstatic.com/store_item_assets/steam/apps/1431310/header.jpg",
      "trend_score": 83,
      "growth_pct": 217,
      "sentiment_positive": 93,
      "tags": [
        "Emotional",
        "Indie",
        "Singleplayer",
        "Atmospheric"
      ]
    },
    {
      "app_id": 1088239,
      "name": "Super Emotional",
      "capsule_url": "https://shared.fastly.steamstatic.com/store_item_assets/steam/apps/1088239/header.jpg",
      "trend_score": 93,
      "growth_pct": 50,
      "sentiment_positive": 97,
      "tags": [
        "Emotional",
        "Indie",
        "Singleplayer",
        "Atmospheric"
      ]
    }
  ]
}