{
  "genre_id": "historical",
  "genre_name": "Historical",
  "category": "Theme",
  "supply_count": 2425,
  "demand_count": 6046,
  "growth_pct": 25.6,
  "opportunity_score": 9.9,
  "opportunity_class": "Excellent",
  "heatmap": {
    "reddit": 1814,
    "youtube": 1814,
    "tiktok": 907,
    "steam": 907,
    "bluesky": 504
  },
  "timeline": [
    {
      "month": "Jan",
      "count": 2290
    },
    {
      "month": "Feb",
      "count": 3207
    },
    {
      "month": "Mar",
      "count": 4314
    },
    {
      "month": "Apr",
      "count": 5542
    },
    {
      "month": "May",
      "count": 6023
    },
    {
      "month": "Jun",
      "count": 6327
    }
  ],
  "related_network": [
    "Singleplayer",
    "Indie",
    "Action-Adventure",
    "Open World",
    "Adventure",
    "Action"
  ],
  "games": [
    {
      "app_id": 3751950,
      "name": "Assassin's Creed Black Flag Resynced",
      "capsule_url": "https://shared.fastly.steamstatic.com/store_item_assets/steam/apps/3751950/header.jpg",
      "trend_score": 85,
      "growth_pct": 507,
      "sentiment_positive": 94,
      "tags": [
        "Action-Adventure",
        "Assassins",
        "Pirates",
        "Naval Combat",
        "Stealth",
        "Exploration",
        "Open World",
        "Third Person",
        "Adventure",
        "Historical"
      ]
    },
    {
      "app_id": 1771300,
      "name": "Kingdom Come: Deliverance II",
      "capsule_url": "https://shared.fastly.steamstatic.com/store_item_assets/steam/apps/1771300/header.jpg",
      "trend_score": 88,
      "growth_pct": 584,
      "sentiment_positive": 83,
      "tags": [
        "RPG",
        "Medieval",
        "Open World",
        "Singleplayer",
        "Story Rich",
        "First-Person",
        "Realistic",
        "Adventure",
        "Action",
        "Historical"
      ]
    },
    {
      "app_id": 1158310,
      "name": "Crusader Kings III",
      "capsule_url": "https://shared.fastly.steamstatic.com/store_item_assets/steam/apps/1158310/header.jpg",
      "trend_score": 95,
      "growth_pct": 110,
      "sentiment_positive": 94,
      "tags": [
        "Historical",
        "Indie",
        "Singleplayer"
      ]
    },
    {
      "app_id": 394360,
      "name": "Hearts of Iron IV",
      "capsule_url": "https://shared.fastly.steamstatic.com/store_item_assets/steam/apps/394360/header.jpg",
      "trend_score": 88,
      "growth_pct": 373,
      "sentiment_positive": 90,
      "tags": [
        "Historical",
        "Indie",
        "Singleplayer"
      ]
    },
    {
      "app_id": 261550,
      "name": "Mount &amp; Blade II: Bannerlord",
      "capsule_url": "https://shared.fastly.steamstatic.com/store_item_assets/steam/apps/261550/header.jpg",
      "trend_score": 77,
      "growth_pct": 502,
      "sentiment_positive": 94,
      "tags": [
        "Historical",
        "Indie",
        "Singleplayer"
      ]
    },
    {
      "app_id": 2215430,
      "name": "Ghost of Tsushima DIRECTOR'S CUT",
      "capsule_url": "https://shared.fastly.steamstatic.com/store_item_assets/steam/apps/2215430/header.jpg",
      "trend_score": 77,
      "growth_pct": 340,
      "sentiment_positive": 85,
      "tags": [
        "Historical",
        "Indie",
        "Singleplayer"
      ]
    },
    {
      "app_id": 3105440,
      "name": "Heroes of Might and Magic: Olden Era",
      "capsule_url": "https://shared.fastly.steamstatic.com/store_item_assets/steam/apps/3105440/header.jpg",
      "trend_score": 94,
      "growth_pct": 268,
      "sentiment_positive": 81,
      "tags": [
        "Historical",
        "Indie",
        "Singleplayer"
      ]
    },
    {
      "app_id": 1295660,
      "name": "Sid Meier's Civilization VII",
      "capsule_url": "https://shared.fastly.steamstatic.com/store_item_assets/steam/apps/1295660/header.jpg",
      "trend_score": 87,
      "growth_pct": 115,
      "sentiment_positive": 85,
      "tags": [
        "Historical",
        "Indie",
        "Singleplayer"
      ]
    },
    {
      "app_id": 3159330,
      "name": "Assassin\u2019s Creed Shadows",
      "capsule_url": "https://shared.fastly.steamstatic.com/store_item_assets/steam/apps/3159330/header.jpg",
      "trend_score": 82,
      "growth_pct": 256,
      "sentiment_positive": 82,
      "tags": [
        "Historical",
        "Indie",
        "Singleplayer"
      ]
    },
    {
      "app_id": 1466860,
      "name": "Age of Empires IV: Anniversary Edition",
      "capsule_url": "https://shared.fastly.steamstatic.com/store_item_assets/steam/apps/1466860/header.jpg",
      "trend_score": 77,
      "growth_pct": 270,
      "sentiment_positive": 87,
      "tags": [
        "Historical",
        "Indie",
        "Singleplayer"
      ]
    },
    {
      "app_id": 813780,
      "name": "Age of Empires II: Definitive Edition",
      "capsule_url": "https://shared.fastly.steamstatic.com/store_item_assets/steam/apps/813780/header.jpg",
      "trend_score": 78,
      "growth_pct": 571,
      "sentiment_positive": 86,
      "tags": [
        "Historical",
        "Indie",
        "Singleplayer"
      ]
    },
    {
      "app_id": 552990,
      "name": "World of Warships",
      "capsule_url": "https://shared.fastly.steamstatic.com/store_item_assets/steam/apps/552990/header.jpg",
      "trend_score": 72,
      "growth_pct": 288,
      "sentiment_positive": 86,
      "tags": [
        "Historical",
        "Indie",
        "Singleplayer"
      ]
    },
    {
      "app_id": 812140,
      "name": "Assassin's Creed\u00ae Odyssey",
      "capsule_url": "https://shared.fastly.steamstatic.com/store_item_assets/steam/apps/812140/header.jpg",
      "trend_score": 75,
      "growth_pct": 201,
      "sentiment_positive": 82,
      "tags": [
        "Historical",
        "Indie",
        "Singleplayer"
      ]
    },
    {
      "app_id": 2677660,
      "name": "Indiana Jones and the Great Circle",
      "capsule_url": "https://shared.fastly.steamstatic.com/store_item_assets/steam/apps/2677660/header.jpg",
      "trend_score": 84,
      "growth_pct": 467,
      "sentiment_positive": 85,
      "tags": [
        "Historical",
        "Indie",
        "Singleplayer"
      ]
    },
    {
      "app_id": 1182900,
      "name": "A Plague Tale: Requiem",
      "capsule_url": "https://shared.fastly.steamstatic.com/store_item_assets/steam/apps/1182900/header.jpg",
      "trend_score": 94,
      "growth_pct": 535,
      "sentiment_positive": 89,
      "tags": [
        "Historical",
        "Indie",
        "Singleplayer"
      ]
    },
    {
      "app_id": 752590,
      "name": "A Plague Tale: Innocence",
      "capsule_url": "https://shared.fastly.steamstatic.com/store_item_assets/steam/apps/752590/header.jpg",
      "trend_score": 79,
      "growth_pct": 414,
      "sentiment_positive": 92,
      "tags": [
        "Historical",
        "Indie",
        "Singleplayer"
      ]
    },
    {
      "app_id": 289070,
      "name": "Sid Meier\u2019s Civilization\u00ae VI",
      "capsule_url": "https://shared.fastly.steamstatic.com/store_item_assets/steam/apps/289070/header.jpg",
      "trend_score": 82,
      "growth_pct": 224,
      "sentiment_positive": 96,
      "tags": [
        "Historical",
        "Indie",
        "Singleplayer"
      ]
    },
    {
      "app_id": 1407200,
      "name": "World of Tanks",
      "capsule_url": "https://shared.fastly.steamstatic.com/store_item_assets/steam/apps/1407200/header.jpg",
      "trend_score": 88,
      "growth_pct": 472,
      "sentiment_positive": 83,
      "tags": [
        "Historical",
        "Indie",
        "Singleplayer"
      ]
    },
    {
      "app_id": 1363080,
      "name": "Manor Lords",
      "capsule_url": "https://shared.fastly.steamstatic.com/store_item_assets/steam/apps/1363080/header.jpg",
      "trend_score": 83,
      "growth_pct": 497,
      "sentiment_positive": 81,
      "tags": [
        "Historical",
        "Indie",
        "Singleplayer"
      ]
    },
    {
      "app_id": 400750,
      "name": "Call to Arms - Gates of Hell: Ostfront",
      "capsule_url": "https://shared.fastly.steamstatic.com/store_item_assets/steam/apps/400750/header.jpg",
      "trend_score": 95,
      "growth_pct": 444,
      "sentiment_positive": 89,
      "tags": [
        "Historical",
        "Indie",
        "Singleplayer"
      ]
    },
    {
      "app_id": 3274580,
      "name": "Anno 117: Pax Romana",
      "capsule_url": "https://shared.fastly.steamstatic.com/store_item_assets/steam/apps/3274580/header.jpg",
      "trend_score": 84,
      "growth_pct": 469,
      "sentiment_positive": 96,
      "tags": [
        "Historical",
        "Indie",
        "Singleplayer"
      ]
    },
    {
      "app_id": 529340,
      "name": "Victoria 3",
      "capsule_url": "https://shared.fastly.steamstatic.com/store_item_assets/steam/apps/529340/header.jpg",
      "trend_score": 72,
      "growth_pct": 294,
      "sentiment_positive": 81,
      "tags": [
        "Historical",
        "Indie",
        "Singleplayer"
      ]
    },
    {
      "app_id": 379430,
      "name": "Kingdom Come: Deliverance",
      "capsule_url": "https://shared.fastly.steamstatic.com/store_item_assets/steam/apps/379430/header.jpg",
      "trend_score": 71,
      "growth_pct": 110,
      "sentiment_positive": 79,
      "tags": [
        "Historical",
        "Indie",
        "Singleplayer"
      ]
    },
    {
      "app_id": 1044720,
      "name": "Farthest Frontier",
      "capsule_url": "https://shared.fastly.steamstatic.com/store_item_assets/steam/apps/1044720/header.jpg",
      "trend_score": 91,
      "growth_pct": 360,
      "sentiment_positive": 94,
      "tags": [
        "Historical",
        "Indie",
        "Singleplayer"
      ]
    },
    {
      "app_id": 582160,
      "name": "Assassin's Creed\u00ae Origins",
      "capsule_url": "https://shared.fastly.steamstatic.com/store_item_assets/steam/apps/582160/header.jpg",
      "trend_score": 73,
      "growth_pct": 156,
      "sentiment_positive": 92,
      "tags": [
        "Historical",
        "Indie",
        "Singleplayer"
      ]
    }
  ]
}