{
  "Action": [
    "Singleplayer",
    "Indie",
    "FPS",
    "Shooter",
    "Multiplayer",
    "Competitive"
  ],
  "RPG": [
    "Indie",
    "Singleplayer",
    "Online Co-Op",
    "Co-op",
    "Third-Person Shooter",
    "Action"
  ],
  "Adventure": [
    "Indie",
    "Singleplayer",
    "Open World",
    "Action",
    "Exploration",
    "Survival"
  ],
  "Strategy": [
    "Indie",
    "Singleplayer",
    "FPS",
    "Shooter",
    "Multiplayer",
    "Competitive"
  ],
  "Puzzle": [
    "Singleplayer",
    "Indie",
    "Relaxing",
    "Simulation",
    "Atmospheric",
    "Magic"
  ],
  "Simulation": [
    "Singleplayer",
    "Indie",
    "Multiplayer",
    "Realistic",
    "Sports",
    "Online Co-Op"
  ],
  "Sports": [
    "Singleplayer",
    "Indie",
    "Multiplayer",
    "Simulation",
    "Realistic",
    "Online Co-Op"
  ],
  "Platformer": [
    "Indie",
    "Singleplayer",
    "Character Customization",
    "Multiplayer",
    "Co-op",
    "MMORPG"
  ],
  "Racing": [
    "Singleplayer",
    "Indie",
    "Open World",
    "Multiplayer",
    "Automobile Sim",
    "Atmospheric"
  ],
  "Fighting": [
    "Singleplayer",
    "Indie",
    "Character Customization",
    "Action",
    "Multiplayer",
    "Adventure"
  ],
  "Shooter": [
    "Indie",
    "Singleplayer",
    "FPS",
    "Multiplayer",
    "Action",
    "Team-Based"
  ],
  "Horror": [
    "Indie",
    "Singleplayer",
    "Gore",
    "Co-op",
    "Violent",
    "First-Person"
  ],
  "Sandbox": [
    "Indie",
    "Singleplayer",
    "Open World",
    "Multiplayer",
    "Online Co-Op",
    "Co-op"
  ],
  "Visual Novel": [
    "Singleplayer",
    "Indie",
    "Story Rich",
    "Strategy",
    "Action",
    "Lore-Rich"
  ],
  "Survival": [
    "Indie",
    "Singleplayer",
    "Multiplayer",
    "Online Co-Op",
    "Co-op",
    "Action"
  ],
  "Point & Click": [
    "Indie",
    "Singleplayer",
    "Atmospheric"
  ],
  "Casual": [
    "Indie",
    "Singleplayer",
    "Atmospheric"
  ],
  "Indie": [
    "Singleplayer",
    "Atmospheric"
  ],
  "Massively Multiplayer": [
    "Indie",
    "Singleplayer",
    "Atmospheric"
  ],
  "Roguelike": [
    "Indie",
    "Singleplayer",
    "Atmospheric"
  ],
  "Roguelite": [
    "Indie",
    "Singleplayer",
    "Atmospheric"
  ],
  "Bullet Heaven": [
    "Indie",
    "Singleplayer",
    "Atmospheric"
  ],
  "Metroidvania": [
    "Singleplayer",
    "Indie",
    "Life Sim",
    "Building",
    "Simulation",
    "Sandbox"
  ],
  "Soulslike": [
    "Indie",
    "Singleplayer",
    "Horror",
    "Gore",
    "Co-op",
    "Violent"
  ],
  "Immersive Sim": [
    "Singleplayer",
    "Indie",
    "Strategy",
    "Card Game",
    "Free to Play",
    "Trading Card Game"
  ],
  "Walking Simulator": [
    "Singleplayer",
    "Indie",
    "RPG",
    "Action",
    "Adventure",
    "Realistic"
  ],
  "Bullet Hell": [
    "Singleplayer",
    "Indie",
    "Great Soundtrack",
    "Soundtrack",
    "Story Rich",
    "Pixel Graphics"
  ],
  "Colony Sim": [
    "Singleplayer",
    "Indie",
    "RPG",
    "Action RPG",
    "JRPG",
    "Surreal"
  ],
  "City Builder": [
    "Singleplayer",
    "Indie",
    "Free to Play",
    "Turn-Based Tactics",
    "Great Soundtrack",
    "Strategy"
  ],
  "Tower Defense": [
    "Indie",
    "Singleplayer",
    "Open World",
    "Survival",
    "Multiplayer",
    "Open World Survival Craft"
  ],
  "Hack and Slash": [
    "Singleplayer",
    "Indie",
    "Action RPG",
    "Action",
    "RPG",
    "Third Person"
  ],
  "Turn-Based Strategy": [
    "Singleplayer",
    "Indie",
    "Free to Play",
    "Strategy",
    "Story Rich",
    "Lore-Rich"
  ],
  "Real-Time Strategy": [
    "Singleplayer",
    "Indie",
    "Multiplayer",
    "Strategy",
    "Competitive",
    "Action"
  ],
  "Action RPG": [
    "Singleplayer",
    "Indie",
    "Free to Play",
    "Action",
    "Third Person",
    "Online Co-Op"
  ],
  "Turn-Based RPG": [
    "Indie",
    "Singleplayer",
    "Multiplayer",
    "Action",
    "Team-Based",
    "First-Person"
  ],
  "Tactical RPG": [
    "Indie",
    "Singleplayer",
    "Multiplayer",
    "PvP",
    "Online Co-Op",
    "Action RTS"
  ],
  "CRPG": [
    "Indie",
    "Singleplayer",
    "Atmospheric"
  ],
  "FPS": [
    "Indie",
    "Singleplayer",
    "Atmospheric"
  ],
  "JRPG": [
    "Indie",
    "Singleplayer",
    "Atmospheric"
  ],
  "Third-Person Shooter": [
    "Singleplayer",
    "Indie",
    "Third Person",
    "Action",
    "Parkour",
    "Action-Adventure"
  ],
  "Twin Stick Shooter": [
    "Indie",
    "Singleplayer",
    "Action Roguelike",
    "Action",
    "Dungeon Crawler",
    "Dark"
  ],
  "Top-Down Shooter": [
    "Singleplayer",
    "Indie",
    "Action-Adventure",
    "Top-Down",
    "Pixel Graphics",
    "2D Platformer"
  ],
  "Boomer Shooter": [
    "Singleplayer",
    "Indie",
    "Action",
    "FPS",
    "Demons",
    "Dark Fantasy"
  ],
  "Survival Horror": [
    "Indie",
    "Singleplayer",
    "Multiplayer",
    "Online Co-Op",
    "Survival",
    "First-Person"
  ],
  "Battle Royale": [
    "Indie",
    "Singleplayer",
    "Multiplayer",
    "FPS",
    "Shooter",
    "First-Person"
  ],
  "Open World Survival Craft": [
    "Indie",
    "Singleplayer",
    "Atmospheric"
  ],
  "Psychological Horror": [
    "Singleplayer",
    "Indie",
    "Story Rich",
    "RPG",
    "Great Soundtrack",
    "Open World"
  ],
  "Life Sim": [
    "Singleplayer",
    "Indie",
    "Character Customization",
    "Simulation",
    "Sandbox",
    "Relaxing"
  ],
  "Dating Sim": [
    "Indie",
    "Singleplayer",
    "Atmospheric"
  ],
  "Management": [
    "Singleplayer",
    "Indie",
    "Simulation",
    "Multiplayer",
    "Immersive Sim",
    "Sports"
  ],
  "Farming Sim": [
    "Singleplayer",
    "Indie",
    "Relaxing",
    "Life Sim",
    "Character Customization",
    "Simulation"
  ],
  "Tycoon": [
    "Singleplayer",
    "Indie",
    "Exploration",
    "Lovecraftian",
    "Adventure",
    "Psychological Horror"
  ],
  "Precision Platformer": [
    "Indie",
    "Singleplayer",
    "Multiplayer",
    "Action",
    "Team-Based",
    "First-Person"
  ],
  "3D Platformer": [
    "Singleplayer",
    "Indie",
    "2D Platformer",
    "Platformer",
    "2D",
    "MMORPG"
  ],
  "Dungeon Crawler": [
    "Indie",
    "Singleplayer",
    "Atmospheric"
  ],
  "Puzzle Platformer": [
    "Indie",
    "Singleplayer",
    "Atmospheric"
  ],
  "Card Game": [
    "Indie",
    "Singleplayer",
    "Atmospheric"
  ],
  "Auto Battler": [
    "Indie",
    "Singleplayer",
    "Atmospheric"
  ],
  "4X": [
    "Indie",
    "Singleplayer",
    "Atmospheric"
  ],
  "Grand Strategy": [
    "Indie",
    "Singleplayer",
    "Atmospheric"
  ],
  "Social Deduction": [
    "Indie",
    "Singleplayer",
    "Roguelike",
    "Co-op",
    "Difficult",
    "Roguelite"
  ],
  "Interactive Fiction": [
    "Singleplayer",
    "Indie",
    "Story Rich",
    "Atmospheric",
    "Adventure",
    "Exploration"
  ],
  "Text-Based": [
    "Indie",
    "Singleplayer",
    "Dating Sim",
    "Visual Novel",
    "LGBTQ+",
    "Romance"
  ],
  "Deckbuilder": [
    "Indie",
    "Singleplayer",
    "Atmospheric"
  ],
  "Automation": [
    "Indie",
    "Singleplayer",
    "Atmospheric"
  ],
  "Base Building": [
    "Singleplayer",
    "Indie",
    "Exploration",
    "Lovecraftian",
    "Adventure",
    "Psychological Horror"
  ],
  "Stealth": [
    "Indie",
    "Singleplayer",
    "FPS",
    "Shooter",
    "Multiplayer",
    "Action"
  ],
  "Parkour": [
    "Singleplayer",
    "Indie",
    "Boxing",
    "Sports",
    "Early Access",
    "Simulation"
  ],
  "Crafting": [
    "Indie",
    "Singleplayer",
    "Open World",
    "Survival",
    "Multiplayer",
    "Open World Survival Craft"
  ],
  "Procedural Generation": [
    "Indie",
    "Singleplayer",
    "Multiplayer",
    "Co-op",
    "Card Game",
    "Gambling"
  ],
  "Physics": [
    "Singleplayer",
    "Indie",
    "Sports",
    "Simulation",
    "Tennis",
    "Realistic"
  ],
  "Resource Management": [
    "Singleplayer",
    "Indie",
    "Multiplayer",
    "Simulation",
    "Sandbox",
    "Gambling"
  ],
  "Character Customization": [
    "Singleplayer",
    "Indie",
    "Free to Play",
    "Action",
    "Co-op",
    "Sci-fi"
  ],
  "Choices Matter": [
    "Singleplayer",
    "Indie",
    "Open World",
    "Free to Play",
    "Multiplayer",
    "Souls-like"
  ],
  "Level Editor": [
    "Singleplayer",
    "Indie",
    "Psychological Horror",
    "Gun Customization",
    "Shooter",
    "Tactical"
  ],
  "Moddable": [
    "Indie",
    "Singleplayer",
    "Atmospheric"
  ],
  "Incremental": [
    "Indie",
    "Singleplayer",
    "Atmospheric"
  ],
  "Idle": [
    "Indie",
    "Singleplayer",
    "Atmospheric"
  ],
  "Building": [
    "Indie",
    "Singleplayer",
    "Atmospheric"
  ],
  "Trading": [
    "Singleplayer",
    "Indie",
    "First-Person",
    "Action",
    "Action-Adventure",
    "Realistic"
  ],
  "Destruction": [
    "Singleplayer",
    "Indie",
    "Demons",
    "Dark Fantasy",
    "Gore",
    "Story Rich"
  ],
  "Investigation": [
    "Indie",
    "Singleplayer",
    "Multiplayer",
    "Online Co-Op",
    "Comedy",
    "Co-op"
  ],
  "Cozy": [
    "Indie",
    "Singleplayer",
    "Atmospheric"
  ],
  "Hidden Object": [
    "Singleplayer",
    "Indie",
    "Multiplayer",
    "Online Co-Op",
    "Voxel",
    "Sandbox"
  ],
  "Dark": [
    "Indie",
    "Singleplayer",
    "Multiplayer",
    "Funny",
    "Comedy",
    "Co-op"
  ],
  "Sci-fi": [
    "Singleplayer",
    "Indie",
    "Free to Play",
    "Action",
    "Character Customization",
    "Co-op"
  ],
  "Dark Fantasy": [
    "Singleplayer",
    "Indie",
    "Action RPG",
    "RPG",
    "Souls-like",
    "Action"
  ],
  "Cyberpunk": [
    "Singleplayer",
    "Indie",
    "FPS",
    "First-Person",
    "Action",
    "Sci-fi"
  ],
  "Steampunk": [
    "Singleplayer",
    "Indie",
    "Multiplayer",
    "Action RPG",
    "Fantasy",
    "Online Co-Op"
  ],
  "Post-apocalyptic": [
    "Singleplayer",
    "Indie",
    "Exploration",
    "Lovecraftian",
    "Adventure",
    "Psychological Horror"
  ],
  "Historical": [
    "Singleplayer",
    "Indie",
    "Action-Adventure",
    "Open World",
    "Adventure",
    "Action"
  ],
  "Medieval": [
    "Singleplayer",
    "Indie",
    "RPG",
    "Open World",
    "Story Rich",
    "Adventure"
  ],
  "Fantasy": [
    "Singleplayer",
    "Indie",
    "Multiplayer",
    "Action RPG",
    "Online Co-Op",
    "Action"
  ],
  "Space": [
    "Indie",
    "Singleplayer",
    "Atmospheric"
  ],
  "Mystery": [
    "Indie",
    "Singleplayer",
    "Atmospheric"
  ],
  "Detective": [
    "Indie",
    "Singleplayer",
    "Atmospheric"
  ],
  "Zombies": [
    "Indie",
    "Singleplayer",
    "Atmospheric"
  ],
  "Pirates": [
    "Indie",
    "Singleplayer",
    "Atmospheric"
  ],
  "Murder Mystery": [
    "Indie",
    "Singleplayer",
    "Atmospheric"
  ],
  "Retro": [
    "Indie",
    "Singleplayer",
    "Funny",
    "Comedy",
    "Mystery",
    "Multiplayer"
  ],
  "Anime": [
    "Indie",
    "Singleplayer",
    "Open World",
    "Multiplayer",
    "Co-op",
    "Adventure"
  ],
  "Pixel Art": [
    "Singleplayer",
    "Indie",
    "Great Soundtrack",
    "Pixel Graphics",
    "2D",
    "Dark"
  ],
  "Minimalist": [
    "Singleplayer",
    "Indie",
    "Action RPG",
    "Online Co-Op",
    "Action",
    "Multiplayer"
  ],
  "Wholesome": [
    "Singleplayer",
    "Indie",
    "Casual",
    "Relaxing",
    "Simulation",
    "3D"
  ],
  "Cute": [
    "Indie",
    "Singleplayer",
    "Multiplayer",
    "Casual",
    "Co-op",
    "Party Game"
  ],
  "Creature Collector": [
    "Singleplayer",
    "Indie",
    "Open World",
    "Multiplayer",
    "Action RPG",
    "Character Customization"
  ],
  "Lovecraftian": [
    "Indie",
    "Singleplayer",
    "Sexual Content",
    "Action",
    "Multiplayer",
    "Shooter"
  ],
  "Military": [
    "Indie",
    "Singleplayer",
    "Multiplayer",
    "Funny",
    "Co-op",
    "Team-Based"
  ],
  "Western": [
    "Indie",
    "Singleplayer",
    "FPS",
    "Shooter",
    "Multiplayer",
    "Action"
  ],
  "Dinosaurs": [
    "Singleplayer",
    "Indie",
    "Strategy",
    "Card Game",
    "Free to Play",
    "Trading Card Game"
  ],
  "Underwater": [
    "Indie",
    "Singleplayer",
    "Survival",
    "Open World",
    "Multiplayer",
    "Simulation"
  ],
  "Robots": [
    "Indie",
    "Singleplayer",
    "Atmospheric"
  ],
  "Magic": [
    "Indie",
    "Singleplayer",
    "Multiplayer",
    "Funny",
    "Co-op",
    "Team-Based"
  ],
  "Singleplayer": [
    "Indie",
    "Atmospheric"
  ],
  "Co-op": [
    "Indie",
    "Singleplayer",
    "Atmospheric"
  ],
  "Online Co-Op": [
    "Indie",
    "Singleplayer",
    "Atmospheric"
  ],
  "Multiplayer": [
    "Indie",
    "Singleplayer",
    "Atmospheric"
  ],
  "PvP": [
    "Indie",
    "Singleplayer",
    "FPS",
    "Shooter",
    "Multiplayer",
    "Competitive"
  ],
  "Local Co-Op": [
    "Singleplayer",
    "Indie",
    "Simulation",
    "Sports",
    "Competitive",
    "Multiplayer"
  ],
  "Split Screen": [
    "Singleplayer",
    "Indie",
    "Multiplayer",
    "Online Co-Op",
    "Local Multiplayer",
    "Local Co-Op"
  ],
  "Story Rich": [
    "Singleplayer",
    "Indie",
    "Free to Play",
    "Strategy",
    "Turn-Based Strategy",
    "Lore-Rich"
  ],
  "Cinematic": [
    "Singleplayer",
    "Indie",
    "Action",
    "Action-Adventure",
    "Pirates",
    "Assassins"
  ],
  "Atmospheric": [
    "Singleplayer",
    "Indie",
    "Multiplayer",
    "Online Co-Op",
    "Co-op",
    "First-Person"
  ],
  "Emotional": [
    "Indie",
    "Singleplayer",
    "Atmospheric"
  ],
  "Open World": [
    "Indie",
    "Singleplayer",
    "Adventure",
    "Action",
    "Exploration",
    "Survival"
  ],
  "Linear": [
    "Singleplayer",
    "Indie",
    "Action",
    "FPS",
    "Shooter",
    "First-Person"
  ],
  "VR": [
    "Singleplayer",
    "Indie",
    "Multiplayer",
    "Simulation",
    "Realistic",
    "Racing"
  ],
  "2D": [
    "Singleplayer",
    "Indie",
    "Story Rich",
    "Great Soundtrack",
    "RPG",
    "Pixel Graphics"
  ],
  "3D": [
    "Singleplayer",
    "Indie",
    "Third Person",
    "Action",
    "Action-Adventure",
    "Pirates"
  ],
  "First-Person": [
    "Indie",
    "Singleplayer",
    "FPS",
    "Shooter",
    "Multiplayer",
    "Action"
  ],
  "Third Person": [
    "Singleplayer",
    "Indie",
    "Action",
    "Parkour",
    "Action-Adventure",
    "Pirates"
  ],
  "Isometric": [
    "Singleplayer",
    "Indie",
    "Action RPG",
    "Hack and Slash",
    "RPG",
    "MMORPG"
  ]
}